nimi/__init__.py
nimi/cli.py
nimi/client.py
nimi/dyndns.py
nimi/function.py
nimi/handler.py
nimi/route53.py
nimi/scheduler.py
nimi/stack.py
nimi/template.yml
nimi-0.2.0.dist-info/entry_points.txt
nimi-0.2.0.dist-info/WHEEL
nimi-0.2.0.dist-info/METADATA
nimi-0.2.0.dist-info/RECORD
