Metadata-Version: 2.1
Name: nimi
Version: 0.2.0
Summary: Painless Dynamic DNS with AWS
Home-page: https://github.com/martinraag/nimi
License: MIT
Keywords: AWS,DNS,dynamic,Lambda,Route53
Author: Martin Raag
Author-email: hi@mraag.xyz
Requires-Python: >=3.6,<4.0
Classifier: Development Status :: 4 - Beta
Classifier: Environment :: Console
Classifier: Intended Audience :: Developers
Classifier: Intended Audience :: End Users/Desktop
Classifier: License :: OSI Approved :: MIT License
Classifier: Programming Language :: Python :: 3
Classifier: Programming Language :: Python :: 3.6
Classifier: Programming Language :: Python :: 3.7
Classifier: Topic :: Internet :: Name Service (DNS)
Classifier: Topic :: Utilities
Requires-Dist: boto3 (>=1.9,<2.0)
Requires-Dist: click (>=7.0,<8.0)
Requires-Dist: jinja2 (>=2.10,<3.0)
Requires-Dist: requests (>=2.22,<3.0)
Requires-Dist: terminaltables (>=3.1,<4.0)
Project-URL: Repository, https://github.com/martinraag/nimi
